deferrable/__init__.py
deferrable/decorator.py
deferrable/tools.py
deferrable_py-0.1.0.dist-info/licenses/LICENSE
deferrable_py-0.1.0.dist-info/METADATA
deferrable_py-0.1.0.dist-info/WHEEL
deferrable_py-0.1.0.dist-info/top_level.txt
deferrable_py-0.1.0.dist-info/RECORD
