Metadata-Version: 2.4
Name: deferrable-py
Version: 0.1.0
Summary: A lightweight pure-Python implementation of Go's defer
Author-email: Juti Noppornpitak <juti_n@yahoo.co.jp>
License-Expression: Apache-2.0
Requires-Python: >=3.9
License-File: LICENSE
Provides-Extra: build
Requires-Dist: setuptools; extra == "build"
Dynamic: license-file
